bsx_python_sdk/__init__.py
bsx_python_sdk/client/__init__.py
bsx_python_sdk/client/rest/__init__.py
bsx_python_sdk/client/rest/account/__init__.py
bsx_python_sdk/client/rest/account/client.py
bsx_python_sdk/client/rest/account/types.py
bsx_python_sdk/client/rest/base.py
bsx_python_sdk/client/rest/market/__init__.py
bsx_python_sdk/client/rest/market/client.py
bsx_python_sdk/client/rest/market/types.py
bsx_python_sdk/common/__init__.py
bsx_python_sdk/common/exception.py
bsx_python_sdk/common/lock.py
bsx_python_sdk/common/types/__init__.py
bsx_python_sdk/common/types/account.py
bsx_python_sdk/common/types/market.py
bsx_python_sdk/common/utils.py
bsx_python_sdk/instance.py
bsx_python_sdk-0.1.0.dist-info/METADATA
bsx_python_sdk-0.1.0.dist-info/WHEEL
bsx_python_sdk-0.1.0.dist-info/RECORD
