Metadata-Version: 2.1
Name: bsx_python_sdk
Version: 0.1.0
Summary: 
Author: abc
Author-email: vuong.phan@bsx.exchange
Requires-Python: >=3.9,<4.0
Classifier: Programming Language :: Python :: 3
Classifier: Programming Language :: Python :: 3.9
Classifier: Programming Language :: Python :: 3.10
Classifier: Programming Language :: Python :: 3.11
Classifier: Programming Language :: Python :: 3.12
Requires-Dist: eip712-structs-ng (>=2.0.1,<3.0.0)
Requires-Dist: eth-account (>=0.11.0,<0.12.0)
Requires-Dist: requests (>=2.31.0,<3.0.0)
Requires-Dist: typing_extensions (>=4.9.0,<5.0.0)
Requires-Dist: web3 (>=6.15.1,<7.0.0)
